jupyterhub_credit_service/__init__.py
jupyterhub_credit_service/__version__.py
jupyterhub_credit_service/apihandlers.py
jupyterhub_credit_service/authenticator.py
jupyterhub_credit_service/orm.py
jupyterhub_credit_service/spawner.py
jupyterhub_credit_service/templates/page.html
jupyterhub_credit_service-0.3.11.dist-info/METADATA
jupyterhub_credit_service-0.3.11.dist-info/WHEEL
jupyterhub_credit_service-0.3.11.dist-info/entry_points.txt
jupyterhub_credit_service-0.3.11.dist-info/licenses/LICENSE
jupyterhub_credit_service-0.3.11.dist-info/RECORD
