Metadata-Version: 2.4
Name: jupyterhub-credit-service
Version: 0.3.11
Summary: JupyterHub Credit Servce
Project-URL: Documentation, https://github.com/jsc-jupyter/jupyterhub-credit-service#readme
Project-URL: Source, https://github.com/jsc-jupyter/jupyterhub-credit-service
Project-URL: Issues, https://github.com/jsc-jupyter/jupyterhub-credit-service/issues
Author-email: Tim Kreuzer <t.kreuzer@fz-juelich.de>
License: BSD 3-Clause License
License-File: LICENSE
Keywords: jupyterhub
Classifier: Programming Language :: Python :: 3
Requires-Python: >=3.9
Requires-Dist: packaging
Requires-Dist: python-dateutil
Requires-Dist: tornado
Requires-Dist: traitlets
Provides-Extra: test
Requires-Dist: jupyterhub; extra == 'test'
Requires-Dist: jupyterlab; extra == 'test'
Requires-Dist: notebook; extra == 'test'
Requires-Dist: psutil; extra == 'test'
Requires-Dist: pytest; extra == 'test'
Requires-Dist: pytest-asyncio; extra == 'test'
Requires-Dist: pytest-cov; extra == 'test'
